tests/__init__.py
tests/test_async_google.py
tests/test_async_wordstat.py
tests/test_async_yandex.py
tests/test_exceptions.py
tests/test_formatters_extended.py
tests/test_geo_data.py
tests/test_geo_public_api.py
tests/test_utils.py
tests/test_validators_extended.py
xmlriver_pro/__init__.py
xmlriver_pro/core/__init__.py
xmlriver_pro/core/async_base_client.py
xmlriver_pro/core/exceptions.py
xmlriver_pro/core/types.py
xmlriver_pro/google/__init__.py
xmlriver_pro/google/async_client.py
xmlriver_pro/utils/__init__.py
xmlriver_pro/utils/formatters.py
xmlriver_pro/utils/geo_data_builtin.py
xmlriver_pro/utils/validators.py
xmlriver_pro/wordstat/__init__.py
xmlriver_pro/wordstat/async_client.py
xmlriver_pro/yandex/__init__.py
xmlriver_pro/yandex/async_client.py
xmlriver_pro-2.2.0.dist-info/licenses/LICENSE
xmlriver_pro-2.2.0.dist-info/METADATA
xmlriver_pro-2.2.0.dist-info/WHEEL
xmlriver_pro-2.2.0.dist-info/top_level.txt
xmlriver_pro-2.2.0.dist-info/RECORD
