Metadata-Version: 2.4
Name: xmlriver-pro
Version: 2.2.0
Summary: Professional Python client for XMLRiver API with Wordstat support
Home-page: https://github.com/xmlriver-pro/xmlriver-pro
Author: XMLRiver Pro Team
Author-email: XMLRiver Pro Team <seo@controlseo.ru>
License: MIT
Project-URL: Homepage, https://xmlriver.com
Project-URL: Repository, https://github.com/Eapwrk/xmlriver-pro
Project-URL: Bug Reports, https://github.com/Eapwrk/xmlriver-pro/issues
Project-URL: Original Repository, https://github.com/KursHub-ru/xmlriver
Keywords: xmlriver,google,yandex,wordstat,search,api,seo,scraping,search-engine,news,images,maps,ads,frequency,keywords
Classifier: Development Status :: 5 - Production/Stable
Classifier: Intended Audience :: Developers
Classifier: License :: OSI Approved :: MIT License
Classifier: Operating System :: OS Independent
Classifier: Programming Language :: Python :: 3
Classifier: Programming Language :: Python :: 3.10
Classifier: Programming Language :: Python :: 3.11
Classifier: Programming Language :: Python :: 3.12
Classifier: Topic :: Internet :: WWW/HTTP :: Dynamic Content
Classifier: Topic :: Software Development :: Libraries :: Python Modules
Classifier: Topic :: Text Processing :: Markup :: XML
Requires-Python: >=3.10
License-File: LICENSE
Requires-Dist: requests>=2.31.0
Requires-Dist: xmltodict>=0.13.0
Requires-Dist: aiohttp>=3.8.0
Provides-Extra: dev
Requires-Dist: pytest>=7.0.0; extra == "dev"
Requires-Dist: pytest-cov>=4.0.0; extra == "dev"
Requires-Dist: black>=23.0.0; extra == "dev"
Requires-Dist: pylint>=2.17.0; extra == "dev"
Requires-Dist: mypy>=1.0.0; extra == "dev"
Requires-Dist: pre-commit>=3.0.0; extra == "dev"
Provides-Extra: docs
Requires-Dist: sphinx>=6.0.0; extra == "docs"
Requires-Dist: sphinx-rtd-theme>=1.2.0; extra == "docs"
Requires-Dist: myst-parser>=1.0.0; extra == "docs"
Dynamic: author
Dynamic: home-page
Dynamic: license-file
Dynamic: requires-python
